phenopype_plugins/__init__.py
phenopype_plugins/utils.py
phenopype_plugins/plugins/__init__.py
phenopype_plugins/plugins/measurement.py
phenopype_plugins/plugins/segmentation.py
phenopype_plugins-0.2.0.dist-info/LICENSE
phenopype_plugins-0.2.0.dist-info/METADATA
phenopype_plugins-0.2.0.dist-info/WHEEL
phenopype_plugins-0.2.0.dist-info/top_level.txt
phenopype_plugins-0.2.0.dist-info/RECORD
