Metadata-Version: 2.2
Name: phenopype-plugins
Version: 0.2.0
Summary: AI and other plugins for phenopype
Author-email: Moritz Lürig <moritz.luerig@gmail.com>
License:                    GNU LESSER GENERAL PUBLIC LICENSE
Project-URL: Homepage, https://phenopype.org
Project-URL: Bug Tracker, https://github.com/phenopype/phenopype-plugins/issues
Keywords: computer vision,biology,ecology,evolution
Requires-Python: >=3.9
License-File: LICENSE
Requires-Dist: phenopype>=5.0
